netdiff/__init__.py
netdiff/exceptions.py
netdiff/info.py
netdiff/tests.py
netdiff/utils.py
netdiff/parsers/__init__.py
netdiff/parsers/base.py
netdiff/parsers/batman.py
netdiff/parsers/bmx6.py
netdiff/parsers/cnml.py
netdiff/parsers/netjson.py
netdiff/parsers/olsr.py
netdiff/parsers/openvpn.py
netdiff/parsers/wireguard.py
netdiff/parsers/zerotier.py
netdiff-1.2.dist-info/licenses/LICENSE
netdiff-1.2.dist-info/METADATA
netdiff-1.2.dist-info/WHEEL
netdiff-1.2.dist-info/top_level.txt
netdiff-1.2.dist-info/RECORD
