Metadata-Version: 2.4
Name: netdiff
Version: 1.2
Summary: Python library for parsing network topology data (eg: dynamic routing protocols, NetJSON, CNML) and detect changes.
Home-page: https://github.com/ninuxorg/netdiff
Download-URL: https://github.com/ninuxorg/netdiff/releases
Author: Federico Capoano
Author-email: federico.capoano@gmail.com
License: MIT
Keywords: networking,mesh-network,netjson,olsr,batman,bmx
Platform: Platform Independent
Classifier: Development Status :: 5 - Production/Stable
Classifier: Environment :: Console
Classifier: Intended Audience :: Developers
Classifier: License :: OSI Approved :: MIT License
Classifier: Operating System :: OS Independent
Classifier: Programming Language :: Python
Classifier: Topic :: System :: Networking
Classifier: Programming Language :: Python :: 3
License-File: LICENSE
Requires-Dist: requests<3.0
Requires-Dist: libcnml<0.10.0
Requires-Dist: openvpn-status<0.3,>=0.2
Requires-Dist: networkx<3.5,>=2.6
Requires-Dist: Exscript>=2.6.32
Dynamic: author
Dynamic: author-email
Dynamic: classifier
Dynamic: description
Dynamic: download-url
Dynamic: home-page
Dynamic: keywords
Dynamic: license
Dynamic: license-file
Dynamic: platform
Dynamic: requires-dist
Dynamic: summary
